smaberta/__init__.py
smaberta/smaberta.py
smaberta-0.0.2.dist-info/LICENSE
smaberta-0.0.2.dist-info/METADATA
smaberta-0.0.2.dist-info/WHEEL
smaberta-0.0.2.dist-info/top_level.txt
smaberta-0.0.2.dist-info/RECORD
