Metadata-Version: 2.1
Name: smaberta
Version: 0.0.2
Summary: a wrapper for the huggingface transformer libraries
Home-page: https://github.com/SMAPPNYU/SMaBERTa.git
Author: Vishakh Padmakumar, Zhanna Terechshenko
License: MIT
Keywords: nlp transformers classification text-classification fine-tuning
Platform: UNKNOWN
Classifier: Programming Language :: Python :: 3
Classifier: License :: OSI Approved :: MIT License
Classifier: Operating System :: OS Independent
Requires-Dist: transformers (==2.6.0)
Requires-Dist: simpletransformers (==0.22.1)
Requires-Dist: pandas
Requires-Dist: torch
Requires-Dist: torchvision
Requires-Dist: tensorboardX
Requires-Dist: tqdm
